odoo_elasticapm/__init__.py
odoo_elasticapm/base.py
odoo_elasticapm/cli.py
odoo_elasticapm/http.py
odoo_elasticapm/ir_cron.py
odoo_elasticapm/ir_http.py
odoo_elasticapm/models.py
odoo_elasticapm-0.0.1.dist-info/METADATA
odoo_elasticapm-0.0.1.dist-info/WHEEL
odoo_elasticapm-0.0.1.dist-info/entry_points.txt
odoo_elasticapm-0.0.1.dist-info/top_level.txt
odoo_elasticapm-0.0.1.dist-info/RECORD
