Metadata-Version: 2.1
Name: odoo-elasticapm
Version: 0.0.1
Summary: Elastic APM integration for Odoo
Home-page: http://github.com/akretion/odoo-elasticapm
Author: Akretion
Author-email: contact@akretion.com
License: AGPLv3+
Platform: UNKNOWN
Classifier: Development Status :: 5 - Production/Stable
Classifier: Intended Audience :: Developers
Classifier: License :: OSI Approved :: GNU Affero General Public License v3 or later (AGPLv3+)
Classifier: Programming Language :: Python :: 2.7
Classifier: Programming Language :: Python :: 3.5
Classifier: Programming Language :: Python :: 3.6
Classifier: Framework :: Odoo
Requires-Dist: elastic-apm (>=5.4)
